ciso-0.2.2.post0.dist-info/zip-safe
ciso-0.2.2.post0.dist-info/RECORD
ciso-0.2.2.post0.dist-info/WHEEL
ciso-0.2.2.post0.dist-info/top_level.txt
ciso-0.2.2.post0.dist-info/LICENSE.txt
ciso-0.2.2.post0.dist-info/METADATA
ciso/_version.py
ciso/_ciso.c
ciso/__init__.py
ciso/_ciso.pyx
ciso/ciso.py
ciso/_ciso.cpython-313-darwin.so
ciso/tests/test_ciso.py
ciso/tests/data/fortran.npz
