Metadata-Version: 2.1
Name: ciso
Version: 0.2.2.post0
Summary: Create isosurfaces from 2D or 3D arrays
Author: Robert Hetland
Author-email: hetland@tamu.edu
License: BSD-2-Clause
Project-URL: homepage, https://github.com/ioos/ciso
Project-URL: documentation, https://ioos.github.io/ciso
Project-URL: repository, https://github.com/ioos/ciso
Platform: any
Requires-Python: >=3.10
License-File: LICENSE.txt
Requires-Dist: numpy
Provides-Extra: extras
Requires-Dist: gridgeo; extra == "extras"
Requires-Dist: cartopy; extra == "extras"
Requires-Dist: xarray; extra == "extras"
